reporter/__init__.py
reporter/reporter.py
fsr_report_generator-0.1.0.dist-info/LICENSE
fsr_report_generator-0.1.0.dist-info/METADATA
fsr_report_generator-0.1.0.dist-info/WHEEL
fsr_report_generator-0.1.0.dist-info/entry_points.txt
fsr_report_generator-0.1.0.dist-info/top_level.txt
fsr_report_generator-0.1.0.dist-info/RECORD
