Metadata-Version: 2.1
Name: fsr-report-generator
Version: 0.1.0
Summary: CLI tool for generating and serving test reports
Home-page: https://github.com/rpluzhnikov/fsr
Author: Roman Pluzhnikov
Author-email: pluzhnikov137@gmail.com
Classifier: Programming Language :: Python :: 3
Classifier: License :: OSI Approved :: MIT License
Classifier: Operating System :: OS Independent
Requires-Python: >=3.6
License-File: LICENSE
